torchstore/__init__.py
torchstore/api.py
torchstore/client.py
torchstore/controller.py
torchstore/logging.py
torchstore/state_dict_utils.py
torchstore/storage_volume.py
torchstore/strategy.py
torchstore/utils.py
torchstore/storage_utils/__init__.py
torchstore/storage_utils/trie.py
torchstore/transport/__init__.py
torchstore/transport/buffers.py
torchstore/transport/pipe.py
torchstore-0.1.2.dist-info/licenses/LICENSE
torchstore-0.1.2.dist-info/METADATA
torchstore-0.1.2.dist-info/WHEEL
torchstore-0.1.2.dist-info/top_level.txt
torchstore-0.1.2.dist-info/RECORD
