Metadata-Version: 2.4
Name: torchstore
Version: 0.1.2
Summary: A storage solution for PyTorch tensors with distributed tensor support
Author-email: PyTorch Team <packages@pytorch.org>
Project-URL: Homepage, https://github.com/meta-pytorch/torchstore
Project-URL: Bug Tracker, https://github.com/meta-pytorch/torchstore/issues
Classifier: Development Status :: 3 - Alpha
Classifier: Intended Audience :: Developers
Classifier: Intended Audience :: Science/Research
Classifier: Programming Language :: Python :: 3.10
Classifier: Programming Language :: Python :: 3.11
Classifier: Topic :: Scientific/Engineering :: Artificial Intelligence
Requires-Python: >=3.10
License-File: LICENSE
Requires-Dist: pygtrie
Requires-Dist: torch==2.9.0
Requires-Dist: torchmonarch==0.1.2
Provides-Extra: dev
Requires-Dist: anyio; extra == "dev"
Requires-Dist: expecttest; extra == "dev"
Requires-Dist: pre-commit; extra == "dev"
Requires-Dist: pytest; extra == "dev"
Requires-Dist: pytest-asyncio; extra == "dev"
Requires-Dist: pytest-cov; extra == "dev"
Requires-Dist: pytest-timeout; extra == "dev"
Requires-Dist: pytest-unordered; extra == "dev"
Requires-Dist: transformers; extra == "dev"
Requires-Dist: ufmt; extra == "dev"
Dynamic: license-file
